<?xml version="1.0" encoding="utf-8" standalone="yes"?>
<PointingMagnifier T="02:07:46:093" eT="13:21:43.0789116">
  <State Active="Initialized" Study="true" Logging="true" Baseline="false">
    <Event>
      <ME Btn="Left" Btn_St="D" Btn_cnt="0" X="497" Y="799" Synth="false" Mag="false" T="02:09:07:343" eT="13:21:44.0789116" />
      <ME Btn="Left" Btn_St="U" Btn_cnt="0" X="497" Y="799" Synth="false" Mag="false" T="02:09:07:359" eT="13:21:44.0789116" />
    </Event>
    <Event>
      <ME Btn="Left" Btn_St="D" Btn_cnt="0" X="494" Y="786" Synth="false" Mag="false" T="02:09:09:171" eT="13:21:45.6726616" />
      <ME Btn="Left" Btn_St="U" Btn_cnt="0" X="494" Y="786" Synth="false" Mag="false" T="02:09:09:171" eT="13:21:45.6726616" />
      <Magnify X="272" Y="536" Diameter="444" TransposeX="0" TransposeY="-28" T="02:09:09:234" eT="13:21:45.6726616" />
      <ME Btn="Left" Btn_St="D" Btn_cnt="-1" X="494" Y="758" Synth="false" Mag="true" T="02:09:09:796" eT="13:21:45.6726616" />
      <ME Btn="Left" Btn_St="U" Btn_cnt="-1" X="494" Y="758" Synth="true" Mag="true" T="02:09:09:796" eT="13:21:45.6726616" />
      <Clickthrough T="02:09:09:796" eT="13:21:45.6726616">
        <DeMagnify T="02:09:09:828" eT="13:21:45.6726616" />
        <ME Btn="Left" Btn_St="D" Btn_cnt="-1" X="494" Y="786" Synth="true" Mag="false" T="02:09:09:859" eT="13:21:45.6726616" />
        <ME Btn="Left" Btn_St="U" Btn_cnt="-1" X="494" Y="786" Synth="false" Mag="false" T="02:09:09:859" eT="13:21:45.6726616" />
      </Clickthrough>
    </Event>
    <Event>
      <ME Btn="Left" Btn_St="D" Btn_cnt="0" X="355" Y="54" Synth="false" Mag="false" T="02:09:14:421" eT="13:21:50.4070366" />
      <ME Btn="Left" Btn_St="U" Btn_cnt="1" X="355" Y="54" Synth="false" Mag="false" T="02:09:14:453" eT="13:21:50.4070366" />
      <Magnify X="133" Y="-60" Diameter="444" TransposeX="0" TransposeY="108" T="02:09:14:515" eT="13:21:50.4070366" />
      <ME Btn="Left" Btn_St="D" Btn_cnt="0" X="355" Y="164" Synth="false" Mag="true" T="02:09:16:953" eT="13:21:52.1414116" />
      <ME Btn="Left" Btn_St="U" Btn_cnt="0" X="355" Y="164" Synth="true" Mag="true" T="02:09:16:953" eT="13:21:52.1414116" />
      <Clickthrough T="02:09:16:953" eT="13:21:52.1414116">
        <DeMagnify T="02:09:16:968" eT="13:21:52.1414116" />
        <ME Btn="Left" Btn_St="D" Btn_cnt="0" X="355" Y="54" Synth="true" Mag="false" T="02:09:17:015" eT="13:21:52.1414116" />
        <ME Btn="Left" Btn_St="U" Btn_cnt="0" X="355" Y="54" Synth="false" Mag="false" T="02:09:17:015" eT="13:21:52.1414116" />
      </Clickthrough>
    </Event>
    <Event>
      <ME Btn="Left" Btn_St="D" Btn_cnt="0" X="355" Y="54" Synth="false" Mag="false" T="02:09:18:515" eT="13:21:54.0632866" />
      <ME Btn="Left" Btn_St="U" Btn_cnt="1" X="355" Y="54" Synth="false" Mag="false" T="02:09:18:562" eT="13:21:54.0632866" />
      <Magnify X="133" Y="-60" Diameter="444" TransposeX="0" TransposeY="108" T="02:09:18:640" eT="13:21:54.0632866" />
      <ME Btn="Left" Btn_St="D" Btn_cnt="0" X="355" Y="162" Synth="false" Mag="true" T="02:09:19:359" eT="13:21:54.9851616" />
      <ME Btn="Left" Btn_St="U" Btn_cnt="0" X="355" Y="162" Synth="true" Mag="true" T="02:09:19:359" eT="13:21:54.9851616" />
      <Clickthrough T="02:09:19:359" eT="13:21:54.9851616">
        <DeMagnify T="02:09:19:375" eT="13:21:54.9851616" />
        <ME Btn="Left" Btn_St="D" Btn_cnt="0" X="355" Y="54" Synth="true" Mag="false" T="02:09:19:421" eT="13:21:54.9851616" />
        <ME Btn="Left" Btn_St="U" Btn_cnt="0" X="355" Y="54" Synth="false" Mag="false" T="02:09:19:421" eT="13:21:54.9851616" />
      </Clickthrough>
    </Event>
    <Event>
      <ME Btn="Left" Btn_St="D" Btn_cnt="0" X="722" Y="226" Synth="false" Mag="false" T="02:09:20:750" eT="13:21:55.9539116" />
      <ME Btn="Left" Btn_St="U" Btn_cnt="0" X="722" Y="226" Synth="false" Mag="false" T="02:09:20:750" eT="13:21:55.9539116" />
    </Event>
    <Event>
      <ME Btn="Left" Btn_St="D" Btn_cnt="0" X="339" Y="67" Synth="false" Mag="false" T="02:09:22:546" eT="13:21:57.8757866" />
      <ME Btn="Left" Btn_St="U" Btn_cnt="1" X="339" Y="67" Synth="false" Mag="false" T="02:09:22:578" eT="13:21:57.8757866" />
      <Magnify X="117" Y="-21" Diameter="444" TransposeX="0" TransposeY="134" T="02:09:22:640" eT="13:21:57.8757866" />
      <ME Btn="Left" Btn_St="D" Btn_cnt="0" X="571" Y="27" Synth="false" Mag="true" T="02:09:24:468" eT="13:21:59.7976616" />
      <ME Btn="Left" Btn_St="U" Btn_cnt="0" X="571" Y="27" Synth="false" Mag="true" T="02:09:24:484" eT="13:21:59.7976616" />
      <DeMagnify T="02:09:25:000" eT="13:21:59.7976616" />
    </Event>
    <Event>
      <ME Btn="Left" Btn_St="D" Btn_cnt="0" X="1049" Y="16" Synth="false" Mag="false" T="02:09:28:718" eT="13:22:03.6882866" />
      <ME Btn="Left" Btn_St="U" Btn_cnt="1" X="1049" Y="16" Synth="false" Mag="false" T="02:09:28:734" eT="13:22:03.6882866" />
      <Magnify X="827" Y="-174" Diameter="444" TransposeX="0" TransposeY="32" T="02:09:28:796" eT="13:22:03.6882866" />
      <ME Btn="Left" Btn_St="D" Btn_cnt="0" X="1041" Y="78" Synth="false" Mag="true" T="02:09:29:453" eT="13:22:04.6570366" />
      <ME Btn="Left" Btn_St="U" Btn_cnt="0" X="1041" Y="78" Synth="true" Mag="true" T="02:09:29:453" eT="13:22:04.6570366" />
      <Clickthrough T="02:09:29:453" eT="13:22:04.6570366">
        <DeMagnify T="02:09:29:484" eT="13:22:04.6570366" />
        <ME Btn="Left" Btn_St="D" Btn_cnt="0" X="1047" Y="26" Synth="true" Mag="false" T="02:09:29:515" eT="13:22:04.6570366" />
        <ME Btn="Left" Btn_St="U" Btn_cnt="0" X="1047" Y="26" Synth="false" Mag="false" T="02:09:29:515" eT="13:22:04.6570366" />
      </Clickthrough>
    </Event>
    <Event>
      <ME Btn="Left" Btn_St="D" Btn_cnt="0" X="1098" Y="786" Synth="false" Mag="false" T="02:09:33:796" eT="13:22:08.5476616" />
      <ME Btn="Left" Btn_St="U" Btn_cnt="0" X="1098" Y="786" Synth="false" Mag="false" T="02:09:33:812" eT="13:22:08.5476616" />
      <ME Btn="Left" Btn_St="D" Btn_cnt="-1" X="1098" Y="786" Synth="false" Mag="false" T="02:09:34:000" eT="13:22:08.5476616" />
      <ME Btn="Left" Btn_St="U" Btn_cnt="0" X="1098" Y="786" Synth="false" Mag="false" T="02:09:34:046" eT="13:22:08.5476616" />
      <Magnify X="836" Y="536" Diameter="444" TransposeX="-40" TransposeY="-28" T="02:09:34:093" eT="13:22:08.5476616" />
      <ME Btn="Left" Btn_St="D" Btn_cnt="-1" X="1058" Y="758" Synth="false" Mag="true" T="02:09:34:765" eT="13:22:09.5320366" />
      <ME Btn="Left" Btn_St="U" Btn_cnt="-1" X="1058" Y="758" Synth="true" Mag="true" T="02:09:34:765" eT="13:22:09.5320366" />
      <Clickthrough T="02:09:34:765" eT="13:22:09.5320366">
        <DeMagnify T="02:09:34:796" eT="13:22:09.5320366" />
        <ME Btn="Left" Btn_St="D" Btn_cnt="-1" X="1098" Y="786" Synth="true" Mag="false" T="02:09:34:828" eT="13:22:09.5320366" />
        <ME Btn="Left" Btn_St="U" Btn_cnt="-1" X="1098" Y="786" Synth="false" Mag="false" T="02:09:34:828" eT="13:22:09.5320366" />
        <ME Btn="Left" Btn_St="D" Btn_cnt="-1" X="1098" Y="786" Synth="false" Mag="false" T="02:09:35:250" eT="13:22:09.5320366" />
        <ME Btn="Left" Btn_St="U" Btn_cnt="-1" X="1098" Y="786" Synth="false" Mag="false" T="02:09:35:265" eT="13:22:09.5320366" />
      </Clickthrough>
    </Event>
    <Event>
      <ME Btn="Left" Btn_St="D" Btn_cnt="0" X="382" Y="214" Synth="false" Mag="false" T="02:09:36:531" eT="13:22:11.5164116" />
      <ME Btn="Left" Btn_St="U" Btn_cnt="1" X="382" Y="214" Synth="false" Mag="false" T="02:09:36:546" eT="13:22:11.5164116" />
      <Magnify X="160" Y="0" Diameter="444" TransposeX="0" TransposeY="8" T="02:09:36:593" eT="13:22:11.5164116" />
      <ME Btn="Left" Btn_St="D" Btn_cnt="0" X="388" Y="170" Synth="false" Mag="true" T="02:09:37:406" eT="13:22:12.4539116" />
      <ME Btn="Left" Btn_St="U" Btn_cnt="0" X="388" Y="170" Synth="true" Mag="true" T="02:09:37:421" eT="13:22:12.4539116" />
      <Clickthrough T="02:09:37:437" eT="13:22:12.4539116">
        <DeMagnify T="02:09:37:484" eT="13:22:12.4539116" />
        <ME Btn="Left" Btn_St="D" Btn_cnt="0" X="384" Y="197" Synth="true" Mag="false" T="02:09:37:515" eT="13:22:12.4539116" />
        <ME Btn="Left" Btn_St="U" Btn_cnt="0" X="384" Y="197" Synth="false" Mag="false" T="02:09:37:515" eT="13:22:12.4539116" />
      </Clickthrough>
    </Event>
    <Event>
      <ME Btn="Left" Btn_St="D" Btn_cnt="0" X="364" Y="615" Synth="false" Mag="false" T="02:09:42:359" eT="13:22:16.8289116" />
      <ME Btn="Left" Btn_St="U" Btn_cnt="1" X="364" Y="615" Synth="false" Mag="false" T="02:09:42:375" eT="13:22:16.8289116" />
      <Magnify X="142" Y="356" Diameter="444" TransposeX="0" TransposeY="-37" T="02:09:42:406" eT="13:22:16.8289116" />
      <ME Btn="Left" Btn_St="D" Btn_cnt="0" X="364" Y="577" Synth="false" Mag="true" T="02:09:43:046" eT="13:22:16.8289116" />
      <ME Btn="Left" Btn_St="U" Btn_cnt="0" X="364" Y="577" Synth="true" Mag="true" T="02:09:43:046" eT="13:22:16.8289116" />
      <Clickthrough T="02:09:43:046" eT="13:22:16.8289116">
        <DeMagnify T="02:09:43:062" eT="13:22:16.8289116" />
        <ME Btn="Left" Btn_St="D" Btn_cnt="0" X="364" Y="615" Synth="true" Mag="false" T="02:09:43:062" eT="13:22:16.8289116" />
        <ME Btn="Left" Btn_St="U" Btn_cnt="1" X="364" Y="615" Synth="false" Mag="false" T="02:09:43:078" eT="13:22:16.8289116" />
      </Clickthrough>
    </Event>
    <Event>
      <ME Btn="Left" Btn_St="D" Btn_cnt="0" X="346" Y="247" Synth="false" Mag="false" T="02:09:46:593" eT="13:22:20.6570366" />
      <ME Btn="Left" Btn_St="U" Btn_cnt="1" X="346" Y="247" Synth="false" Mag="false" T="02:09:46:609" eT="13:22:20.6570366" />
      <Magnify X="124" Y="25" Diameter="444" TransposeX="0" TransposeY="0" T="02:09:46:640" eT="13:22:20.6570366" />
      <ME Btn="Left" Btn_St="D" Btn_cnt="0" X="369" Y="218" Synth="false" Mag="true" T="02:09:48:328" eT="13:22:22.4382866" />
      <ME Btn="Left" Btn_St="U" Btn_cnt="0" X="369" Y="218" Synth="false" Mag="true" T="02:09:48:328" eT="13:22:22.4382866" />
      <ME Btn="Left" Btn_St="U" Btn_cnt="-1" X="369" Y="218" Synth="true" Mag="true" T="02:09:48:328" eT="13:22:22.4382866" />
      <Clickthrough T="02:09:48:328" eT="13:22:22.4382866">
        <DeMagnify T="02:09:48:328" eT="13:22:22.4382866" />
        <ME Btn="Left" Btn_St="D" Btn_cnt="-1" X="353" Y="238" Synth="true" Mag="false" T="02:09:48:406" eT="13:22:22.4382866" />
        <ME Btn="Left" Btn_St="D" Btn_cnt="0" X="360" Y="304" Synth="false" Mag="false" T="02:09:52:765" eT="13:22:26.2195366" />
        <ME Btn="Left" Btn_St="U" Btn_cnt="0" X="360" Y="304" Synth="false" Mag="false" T="02:09:52:765" eT="13:22:26.2195366" />
      </Clickthrough>
    </Event>
    <Event>
      <ME Btn="Left" Btn_St="D" Btn_cnt="0" X="353" Y="305" Synth="false" Mag="false" T="02:09:55:750" eT="13:22:29.0476616" />
      <ME Btn="Left" Btn_St="U" Btn_cnt="1" X="353" Y="305" Synth="false" Mag="false" T="02:09:55:765" eT="13:22:29.0476616" />
      <Magnify X="131" Y="83" Diameter="444" TransposeX="0" TransposeY="0" T="02:09:55:796" eT="13:22:29.0476616" />
      <ME Btn="Left" Btn_St="D" Btn_cnt="0" X="307" Y="305" Synth="false" Mag="true" T="02:09:56:640" eT="13:22:30.0007866" />
      <ME Btn="Left" Btn_St="U" Btn_cnt="0" X="307" Y="305" Synth="true" Mag="true" T="02:09:56:640" eT="13:22:30.0007866" />
      <Clickthrough T="02:09:56:640" eT="13:22:30.0007866">
        <DeMagnify T="02:09:56:640" eT="13:22:30.0007866" />
        <ME Btn="Left" Btn_St="D" Btn_cnt="0" X="338" Y="305" Synth="true" Mag="false" T="02:09:56:671" eT="13:22:30.0007866" />
        <ME Btn="Left" Btn_St="U" Btn_cnt="0" X="338" Y="305" Synth="false" Mag="false" T="02:09:56:671" eT="13:22:30.0007866" />
      </Clickthrough>
    </Event>
  </State>
  <State Study="true" Logging="true" Baseline="false" Active="false" T="02:10:02:531" eT="13:22:35.7664116">
    <Event>
      <ME Btn="Left" Btn_St="D" Btn_cnt="0" X="375" Y="369" Synth="false" Mag="false" T="02:10:12:328" eT="13:22:45.2976616" />
      <ME Btn="Left" Btn_St="U" Btn_cnt="0" X="375" Y="369" Synth="false" Mag="false" T="02:10:12:343" eT="13:22:45.2976616" />
      <ME Btn="Left" Btn_St="D" Btn_cnt="0" X="318" Y="371" Synth="false" Mag="false" T="02:10:19:437" eT="13:22:51.9695366" />
      <ME Btn="Left" Btn_St="U" Btn_cnt="0" X="318" Y="371" Synth="false" Mag="false" T="02:10:19:484" eT="13:22:51.9695366" />
      <ME Btn="Left" Btn_St="D" Btn_cnt="0" X="295" Y="241" Synth="false" Mag="false" T="02:10:28:125" eT="13:22:59.5945366" />
      <ME Btn="Left" Btn_St="U" Btn_cnt="0" X="295" Y="241" Synth="false" Mag="false" T="02:10:28:140" eT="13:22:59.5945366" />
      <ME Btn="Left" Btn_St="D" Btn_cnt="0" X="299" Y="304" Synth="false" Mag="false" T="02:10:32:468" eT="13:23:04.2664116" />
      <ME Btn="Left" Btn_St="U" Btn_cnt="0" X="299" Y="304" Synth="false" Mag="false" T="02:10:32:484" eT="13:23:04.2664116" />
      <ME Btn="Left" Btn_St="D" Btn_cnt="0" X="312" Y="305" Synth="false" Mag="false" T="02:10:34:781" eT="13:23:06.0164116" />
      <ME Btn="Left" Btn_St="U" Btn_cnt="0" X="312" Y="305" Synth="false" Mag="false" T="02:10:34:828" eT="13:23:06.0164116" />
      <ME Btn="Left" Btn_St="D" Btn_cnt="0" X="403" Y="437" Synth="false" Mag="false" T="02:10:42:468" eT="13:23:13.5007866" />
      <ME Btn="Left" Btn_St="U" Btn_cnt="0" X="403" Y="437" Synth="false" Mag="false" T="02:10:42:468" eT="13:23:13.5007866" />
      <ME Btn="Left" Btn_St="D" Btn_cnt="0" X="300" Y="506" Synth="false" Mag="false" T="02:10:52:765" eT="13:23:22.7507866" />
      <ME Btn="Left" Btn_St="U" Btn_cnt="0" X="300" Y="506" Synth="false" Mag="false" T="02:10:52:781" eT="13:23:22.7507866" />
      <ME Btn="Left" Btn_St="D" Btn_cnt="0" X="375" Y="586" Synth="false" Mag="false" T="02:10:56:765" eT="13:23:26.4382866" />
      <ME Btn="Left" Btn_St="U" Btn_cnt="0" X="375" Y="586" Synth="false" Mag="false" T="02:10:56:796" eT="13:23:26.4382866" />
      <ME Btn="Left" Btn_St="D" Btn_cnt="0" X="375" Y="163" Synth="false" Mag="false" T="02:10:59:718" eT="13:23:29.2976616" />
      <ME Btn="Left" Btn_St="U" Btn_cnt="0" X="375" Y="163" Synth="false" Mag="false" T="02:10:59:734" eT="13:23:29.2976616" />
      <ME Btn="Left" Btn_St="D" Btn_cnt="0" X="360" Y="44" Synth="false" Mag="false" T="02:11:01:234" eT="13:23:30.2195366" />
      <ME Btn="Left" Btn_St="U" Btn_cnt="0" X="764" Y="225" Synth="false" Mag="false" T="02:11:03:593" eT="13:23:33.0476616" />
      <ME Btn="Left" Btn_St="D" Btn_cnt="0" X="1039" Y="25" Synth="false" Mag="false" T="02:11:05:484" eT="13:23:34.9226616" />
      <ME Btn="Left" Btn_St="U" Btn_cnt="0" X="1039" Y="25" Synth="false" Mag="false" T="02:11:05:546" eT="13:23:34.9226616" />
      <ME Btn="Left" Btn_St="D" Btn_cnt="0" X="1096" Y="229" Synth="false" Mag="false" T="02:11:07:171" eT="13:23:35.8601616" />
      <ME Btn="Left" Btn_St="U" Btn_cnt="0" X="1096" Y="229" Synth="false" Mag="false" T="02:11:07:203" eT="13:23:35.8601616" />
      <ME Btn="Left" Btn_St="D" Btn_cnt="0" X="1219" Y="141" Synth="false" Mag="false" T="02:11:08:968" eT="13:23:37.7351616" />
      <ME Btn="Left" Btn_St="U" Btn_cnt="0" X="1219" Y="141" Synth="false" Mag="false" T="02:11:08:968" eT="13:23:37.7351616" />
      <ME Btn="Left" Btn_St="D" Btn_cnt="0" X="1122" Y="144" Synth="false" Mag="false" T="02:11:10:312" eT="13:23:39.6414116" />
      <ME Btn="Left" Btn_St="U" Btn_cnt="0" X="1122" Y="144" Synth="false" Mag="false" T="02:11:10:328" eT="13:23:39.6414116" />
      <ME Btn="Left" Btn_St="D" Btn_cnt="0" X="689" Y="217" Synth="false" Mag="false" T="02:11:12:343" eT="13:23:41.5789116" />
      <ME Btn="Left" Btn_St="U" Btn_cnt="0" X="878" Y="282" Synth="false" Mag="false" T="02:11:13:109" eT="13:23:41.5789116" />
      <ME Btn="Left" Btn_St="D" Btn_cnt="0" X="897" Y="286" Synth="false" Mag="false" T="02:11:14:171" eT="13:23:42.5164116" />
      <ME Btn="Left" Btn_St="U" Btn_cnt="0" X="897" Y="286" Synth="false" Mag="false" T="02:11:14:671" eT="13:23:43.4851616" />
      <ME Btn="Left" Btn_St="D" Btn_cnt="0" X="965" Y="285" Synth="false" Mag="false" T="02:11:15:875" eT="13:23:44.4539116" />
      <ME Btn="Left" Btn_St="U" Btn_cnt="0" X="965" Y="285" Synth="false" Mag="false" T="02:11:15:890" eT="13:23:44.4539116" />
      <ME Btn="Left" Btn_St="D" Btn_cnt="0" X="409" Y="162" Synth="false" Mag="false" T="02:11:23:328" eT="13:23:52.0789116" />
      <ME Btn="Left" Btn_St="U" Btn_cnt="0" X="409" Y="162" Synth="false" Mag="false" T="02:11:23:328" eT="13:23:52.0789116" />
      <ME Btn="Left" Btn_St="D" Btn_cnt="0" X="521" Y="74" Synth="false" Mag="false" T="02:11:25:687" eT="13:23:53.9851616" />
      <ME Btn="Left" Btn_St="U" Btn_cnt="0" X="892" Y="201" Synth="false" Mag="false" T="02:11:26:265" eT="13:23:53.9851616" />
      <ME Btn="Left" Btn_St="D" Btn_cnt="0" X="1091" Y="197" Synth="false" Mag="false" T="02:11:27:953" eT="13:23:55.9070366" />
      <ME Btn="Left" Btn_St="U" Btn_cnt="0" X="1091" Y="197" Synth="false" Mag="false" T="02:11:27:968" eT="13:23:55.9070366" />
      <ME Btn="Left" Btn_St="D" Btn_cnt="0" X="562" Y="280" Synth="false" Mag="false" T="02:11:29:390" eT="13:23:57.6414116" />
      <ME Btn="Left" Btn_St="U" Btn_cnt="0" X="562" Y="280" Synth="false" Mag="false" T="02:11:29:406" eT="13:23:57.6414116" />
      <ME Btn="Left" Btn_St="D" Btn_cnt="0" X="435" Y="201" Synth="false" Mag="false" T="02:11:30:250" eT="13:23:57.6414116" />
      <ME Btn="Left" Btn_St="U" Btn_cnt="0" X="771" Y="220" Synth="false" Mag="false" T="02:11:32:187" eT="13:23:59.6570366" />
      <ME Btn="Right" Btn_St="D" Btn_cnt="0" X="1096" Y="777" Synth="false" Mag="false" T="02:11:33:703" eT="13:24:01.4382866" />
      <ME Btn="Right" Btn_St="U" Btn_cnt="0" X="1096" Y="777" Synth="false" Mag="false" T="02:11:33:718" eT="13:24:01.4382866" />
      <ME Btn="Left" Btn_St="D" Btn_cnt="0" X="1059" Y="716" Synth="false" Mag="false" T="02:11:36:968" eT="13:24:04.2351616" />
      <ME Btn="Left" Btn_St="U" Btn_cnt="0" X="1059" Y="716" Synth="false" Mag="false" T="02:11:36:968" eT="13:24:04.2351616" />
      <ME Btn="Left" Btn_St="D" Btn_cnt="0" X="529" Y="92" Synth="false" Mag="false" T="02:11:38:906" eT="13:24:06.0789116" />
      <ME Btn="Left" Btn_St="U" Btn_cnt="0" X="700" Y="46" Synth="false" Mag="false" T="02:11:39:859" eT="13:24:06.9695366" />
      <ME Btn="Left" Btn_St="D" Btn_cnt="0" X="669" Y="150" Synth="false" Mag="false" T="02:11:40:375" eT="13:24:07.9070366" />
      <ME Btn="Left" Btn_St="U" Btn_cnt="0" X="669" Y="150" Synth="false" Mag="false" T="02:11:40:375" eT="13:24:07.9070366" />
      <ME Btn="Left" Btn_St="D" Btn_cnt="0" X="631" Y="60" Synth="false" Mag="false" T="02:11:49:437" eT="13:24:16.4226616" />
      <ME Btn="Left" Btn_St="U" Btn_cnt="0" X="800" Y="286" Synth="false" Mag="false" T="02:11:50:421" eT="13:24:17.3601616" />
      <ME Btn="Left" Btn_St="D" Btn_cnt="0" X="707" Y="286" Synth="false" Mag="false" T="02:12:30:671" eT="13:24:55.0476616" />
      <ME Btn="Left" Btn_St="U" Btn_cnt="0" X="805" Y="412" Synth="false" Mag="false" T="02:12:31:828" eT="13:24:56.0007866" />
      <ME Btn="Left" Btn_St="D" Btn_cnt="0" X="743" Y="412" Synth="false" Mag="false" T="02:13:11:906" eT="13:25:33.5789116" />
      <ME Btn="Left" Btn_St="U" Btn_cnt="0" X="760" Y="363" Synth="false" Mag="false" T="02:13:12:640" eT="13:25:34.5320366" />
      <ME Btn="Left" Btn_St="D" Btn_cnt="0" X="1122" Y="451" Synth="false" Mag="false" T="02:13:13:437" eT="13:25:35.4851616" />
      <ME Btn="Left" Btn_St="U" Btn_cnt="0" X="861" Y="401" Synth="false" Mag="false" T="02:13:13:937" eT="13:25:35.4851616" />
      <ME Btn="Left" Btn_St="D" Btn_cnt="0" X="1194" Y="367" Synth="false" Mag="false" T="02:13:16:593" eT="13:25:38.2976616" />
      <ME Btn="Left" Btn_St="U" Btn_cnt="0" X="1194" Y="367" Synth="false" Mag="false" T="02:13:16:609" eT="13:25:38.2976616" />
      <ME Btn="Left" Btn_St="D" Btn_cnt="0" X="744" Y="213" Synth="false" Mag="false" T="02:13:17:531" eT="13:25:39.2664116" />
      <ME Btn="Left" Btn_St="U" Btn_cnt="0" X="773" Y="129" Synth="false" Mag="false" T="02:13:18:406" eT="13:25:40.2195366" />
      <ME Btn="Left" Btn_St="D" Btn_cnt="0" X="406" Y="166" Synth="false" Mag="false" T="02:13:20:984" eT="13:25:42.1257866" />
      <ME Btn="Left" Btn_St="U" Btn_cnt="0" X="406" Y="166" Synth="false" Mag="false" T="02:13:20:984" eT="13:25:42.1257866" />
      <ME Btn="Left" Btn_St="D" Btn_cnt="0" X="482" Y="136" Synth="false" Mag="false" T="02:13:22:406" eT="13:25:44.0632866" />
      <ME Btn="Left" Btn_St="U" Btn_cnt="0" X="597" Y="231" Synth="false" Mag="false" T="02:13:22:750" eT="13:25:44.0632866" />
      <ME Btn="Left" Btn_St="D" Btn_cnt="0" X="598" Y="297" Synth="false" Mag="false" T="02:13:23:328" eT="13:25:44.9539116" />
      <ME Btn="Left" Btn_St="U" Btn_cnt="0" X="598" Y="297" Synth="false" Mag="false" T="02:13:23:328" eT="13:25:44.9539116" />
      <ME Btn="Left" Btn_St="D" Btn_cnt="0" X="628" Y="297" Synth="false" Mag="false" T="02:13:37:750" eT="13:25:57.9539116" />
      <ME Btn="Left" Btn_St="U" Btn_cnt="0" X="628" Y="297" Synth="false" Mag="false" T="02:13:37:750" eT="13:25:57.9539116" />
      <ME Btn="Left" Btn_St="D" Btn_cnt="0" X="645" Y="297" Synth="false" Mag="false" T="02:13:38:390" eT="13:25:58.6726616" />
      <ME Btn="Left" Btn_St="U" Btn_cnt="0" X="645" Y="297" Synth="false" Mag="false" T="02:13:38:390" eT="13:25:58.6726616" />
      <ME Btn="Left" Btn_St="D" Btn_cnt="0" X="639" Y="234" Synth="false" Mag="false" T="02:13:47:796" eT="13:26:06.8757866" />
      <ME Btn="Left" Btn_St="U" Btn_cnt="0" X="667" Y="302" Synth="false" Mag="false" T="02:13:49:125" eT="13:26:07.7976616" />
      <ME Btn="Left" Btn_St="D" Btn_cnt="0" X="860" Y="367" Synth="false" Mag="false" T="02:14:11:078" eT="13:26:28.5476616" />
      <ME Btn="Left" Btn_St="U" Btn_cnt="0" X="860" Y="367" Synth="false" Mag="false" T="02:14:11:109" eT="13:26:28.5476616" />
      <ME Btn="Left" Btn_St="D" Btn_cnt="0" X="642" Y="409" Synth="false" Mag="false" T="02:14:49:515" eT="13:27:05.0789116" />
      <ME Btn="Left" Btn_St="U" Btn_cnt="0" X="642" Y="409" Synth="false" Mag="false" T="02:14:49:562" eT="13:27:05.0789116" />
    </Event>
  </State>
  <State Study="true" Logging="true" Baseline="false" Active="true" T="02:15:02:546" eT="13:27:17.2976616">
    <Event>
      <ME Btn="Left" Btn_St="D" Btn_cnt="0" X="780" Y="164" Synth="false" Mag="false" T="02:15:07:390" eT="13:27:22.0164116" />
      <ME Btn="Left" Btn_St="U" Btn_cnt="0" X="780" Y="164" Synth="false" Mag="false" T="02:15:07:390" eT="13:27:22.0164116" />
      <Magnify X="558" Y="0" Diameter="444" TransposeX="0" TransposeY="58" T="02:15:07:421" eT="13:27:22.0164116" />
      <ME Btn="Left" Btn_St="D" Btn_cnt="-1" X="580" Y="339" Synth="false" Mag="true" T="02:15:08:593" eT="13:27:22.9695366" />
      <ME Btn="Left" Btn_St="U" Btn_cnt="-1" X="580" Y="339" Synth="false" Mag="true" T="02:15:08:609" eT="13:27:22.9695366" />
      <DeMagnify T="02:15:09:125" eT="13:27:22.9695366" />
    </Event>
    <Event>
      <ME Btn="Left" Btn_St="D" Btn_cnt="0" X="510" Y="174" Synth="false" Mag="false" T="02:15:09:718" eT="13:27:23.9226616" />
      <ME Btn="Left" Btn_St="U" Btn_cnt="1" X="510" Y="174" Synth="false" Mag="false" T="02:15:09:734" eT="13:27:23.9226616" />
      <Magnify X="288" Y="0" Diameter="444" TransposeX="0" TransposeY="48" T="02:15:09:765" eT="13:27:23.9226616" />
      <ME Btn="Left" Btn_St="D" Btn_cnt="0" X="790" Y="162" Synth="false" Mag="true" T="02:15:10:781" eT="13:27:24.8757866" />
      <ME Btn="Left" Btn_St="U" Btn_cnt="0" X="790" Y="162" Synth="false" Mag="true" T="02:15:10:781" eT="13:27:24.8757866" />
      <DeMagnify T="02:15:11:296" eT="13:27:24.8757866" />
    </Event>
    <Event>
      <ME Btn="Left" Btn_St="D" Btn_cnt="0" X="781" Y="438" Synth="false" Mag="false" T="02:15:12:703" eT="13:27:26.7351616" />
      <ME Btn="Left" Btn_St="U" Btn_cnt="0" X="781" Y="438" Synth="false" Mag="false" T="02:15:12:718" eT="13:27:26.7351616" />
    </Event>
  </State>
</PointingMagnifier>